scraparser/__init__.py
scraparser/__main__.py
scraparser/cli/__init__.py
scraparser/cli/click_helpers.py
scraparser/cli/entry_point.py
scraparser/cli/fix.py
scraparser/cli/googlesheet.py
scraparser/cli/parse_pdf.py
scraparser/cli/scrap.py
scraparser/cli/sort.py
scraparser-0.3.1.dist-info/LICENSE
scraparser-0.3.1.dist-info/METADATA
scraparser-0.3.1.dist-info/WHEEL
scraparser-0.3.1.dist-info/top_level.txt
scraparser-0.3.1.dist-info/RECORD
