Metadata-Version: 2.1
Name: scraparser
Version: 0.3.1
Summary: A simplified PDF table scraping and parsing tool
Home-page: https://gitlab.com/yookoala/scraparser
Author: Koala Yeung
Author-email: koalay@gmail.com
License: UNKNOWN
Project-URL: Code, https://gitlab.com/yookoala/scraparser
Project-URL: Issue tracker, https://gitlab.com/yookoala/scraparser/-/issues
Platform: UNKNOWN
Classifier: Programming Language :: Python :: 3 :: Only
Classifier: Programming Language :: Python :: 3.6
Classifier: Programming Language :: Python :: 3.7
Classifier: Programming Language :: Python :: 3.8
Classifier: License :: OSI Approved :: MIT License
Classifier: Operating System :: OS Independent
Classifier: Environment :: Console
Classifier: Topic :: Office/Business :: Financial :: Spreadsheet
Classifier: Topic :: Utilities
Requires-Python: >=3.6
Requires-Dist: camelot-py (>=0.7click>=7.1google-api-python-client>=1.8google-auth-httplib2>=0.0.3google-auth-oauthlib>=0.4opencv-python>=4.2python-magic>=0.4validators>=0.14)
